CHANGES.txt
MANIFEST.in
README.txt
setup.cfg
setup.py
cs/__init__.py
cs.argitalpena.egg-info/PKG-INFO
cs.argitalpena.egg-info/SOURCES.txt
cs.argitalpena.egg-info/dependency_links.txt
cs.argitalpena.egg-info/entry_points.txt
cs.argitalpena.egg-info/namespace_packages.txt
cs.argitalpena.egg-info/not-zip-safe
cs.argitalpena.egg-info/paster_plugins.txt
cs.argitalpena.egg-info/requires.txt
cs.argitalpena.egg-info/top_level.txt
cs/argitalpena/__init__.py
cs/argitalpena/config.py
cs/argitalpena/configure.zcml
cs/argitalpena/interfaces.py
cs/argitalpena/rebuild_i18n.sh
cs/argitalpena/browser/__init__.py
cs/argitalpena/browser/argitalpenak_tabular_view.pt
cs/argitalpena/browser/argitalpenaview.pt
cs/argitalpena/browser/azken_argitalpenak.pt
cs/argitalpena/browser/azken_argitalpenak.py
cs/argitalpena/browser/configure.zcml
cs/argitalpena/content/__init__.py
cs/argitalpena/content/argitalpena.py
cs/argitalpena/content/configure.zcml
cs/argitalpena/locales/cs.argitalpena-manual.pot
cs/argitalpena/locales/cs.argitalpena.pot
cs/argitalpena/locales/es/LC_MESSAGES/cs.argitalpena.mo
cs/argitalpena/locales/es/LC_MESSAGES/cs.argitalpena.po
cs/argitalpena/locales/eu/LC_MESSAGES/cs.argitalpena.mo
cs/argitalpena/locales/eu/LC_MESSAGES/cs.argitalpena.po
cs/argitalpena/profiles/default/factorytool.xml
cs/argitalpena/profiles/default/metadata.xml
cs/argitalpena/profiles/default/propertiestool.xml
cs/argitalpena/profiles/default/rolemap.xml
cs/argitalpena/profiles/default/types.xml
cs/argitalpena/profiles/default/types/DonEdukia.xml
cs/argitalpena/profiles/default/types/argitalpena.xml
docs/INSTALL.txt
docs/LICENSE.GPL
docs/LICENSE.txt