Metadata-Version: 1.1
Name: cs.argitalpena
Version: 2.1
Summary: UNKNOWN
Home-page: http://github.com/codesyntax/cs.argitalpena
Author: Lur Ibargutxi
Author-email: libargutxi@codesyntax.com
License: GPL
Keywords: plone publication file
Platform: UNKNOWN
Classifier: Framework :: Plone
Classifier: Intended Audience :: Developers
Classifier: Topic :: Software Development :: Libraries :: Python Modules
Classifier: License :: OSI Approved :: GNU General Public License (GPL)
